FPGA/pwm.v
module counter_pwm(
    input clk,
    input rst,
    input en,
    output reg pwm,
    output reg [3:0] count
);

always @(posedge clk)
    if(rst)
        count <= 0;
    else if (en) begin
            count <= count + 1;
    end

always @(posedge clk)
    if(count < 4'd8 && count != 0)
    pwm <= 1;
    else
    pwm <= 0;
    
endmodule

FPGA/sim_test/tb_pwm.v

module tb_counter_pwm;

reg clk, rst, en;
wire pwm;
wire [3:0] count;

counter_pwm dut (
    .clk(clk),
    .rst(rst),
    .en(en),
    .pwm(pwm),
    .count(count)
);

initial begin
    clk = 0;
    forever #5 clk = ~clk;
end

initial begin
    $dumpfile("counter_pwm.vcd");
    $dumpvars(0, tb_counter_pwm);

    rst = 1; en = 0;
    #20;
    // count up — pwm HIGH when count < 8
    rst = 0; en = 1;
    #500

    $finish;
end

endmodule

FPGA/sim_test/counter_pwm.vcd
$date
	Mon May 25 17:37:38 2026
$end
$version
	Icarus Verilog
$end
$timescale
	1s
$end
$scope module tb_counter_pwm $end
$var wire 1 ! pwm $end
$var wire 4 " count [3:0] $end
$var reg 1 # clk $end
$var reg 1 $ en $end
$var reg 1 % rst $end
$scope module dut $end
$var wire 1 # clk $end
$var wire 1 $ en $end
$var wire 1 % rst $end
$var reg 4 & count [3:0] $end
$var reg 1 ! pwm $end
$upscope $end
$upscope $end
$enddefinitions $end
$comment Show the parameter values. $end
$dumpall
$end
#0
$dumpvars
bx &
1%
0$
0#
bx "
x!
$end
#5
b0 "
b0 &
0!
1#
#10
0#
#15
1#
#20
0#
1$
0%
#25
b1 "
b1 &
1#
#30
0#
#35
1!
b10 "
b10 &
1#
#40
0#
#45
b11 "
b11 &
1#
#50
0#
#55
b100 "
b100 &
1#
#60
0#
#65
b101 "
b101 &
1#
#70
0#
#75
b110 "
b110 &
1#
#80
0#
#85
b111 "
b111 &
1#
#90
0#
#95
b1000 "
b1000 &
1#
#100
0#
#105
b1001 "
b1001 &
0!
1#
#110
0#
#115
b1010 "
b1010 &
1#
#120
0#
#125
b1011 "
b1011 &
1#
#130
0#
#135
b1100 "
b1100 &
1#
#140
0#
#145
b1101 "
b1101 &
1#
#150
0#
#155
b1110 "
b1110 &
1#
#160
0#
#165
b1111 "
b1111 &
1#
#170
0#
#175
b0 "
b0 &
1#
#180
0#
#185
b1 "
b1 &
1#
#190
0#
#195
1!
b10 "
b10 &
1#
#200
0#
#205
b11 "
b11 &
1#
#210
0#
#215
b100 "
b100 &
1#
#220
0#
#225
b101 "
b101 &
1#
#230
0#
#235
b110 "
b110 &
1#
#240
0#
#245
b111 "
b111 &
1#
#250
0#
#255
b1000 "
b1000 &
1#
#260
0#
#265
b1001 "
b1001 &
0!
1#
#270
0#
#275
b1010 "
b1010 &
1#
#280
0#
#285
b1011 "
b1011 &
1#
#290
0#
#295
b1100 "
b1100 &
1#
#300
0#
#305
b1101 "
b1101 &
1#
#310
0#
#315
b1110 "
b1110 &
1#
#320
0#
#325
b1111 "
b1111 &
1#
#330
0#
#335
b0 "
b0 &
1#
#340
0#
#345
b1 "
b1 &
1#
#350
0#
#355
1!
b10 "
b10 &
1#
#360
0#
#365
b11 "
b11 &
1#
#370
0#
#375
b100 "
b100 &
1#
#380
0#
#385
b101 "
b101 &
1#
#390
0#
#395
b110 "
b110 &
1#
#400
0#
#405
b111 "
b111 &
1#
#410
0#
#415
b1000 "
b1000 &
1#
#420
0#
#425
b1001 "
b1001 &
0!
1#
#430
0#
#435
b1010 "
b1010 &
1#
#440
0#
#445
b1011 "
b1011 &
1#
#450
0#
#455
b1100 "
b1100 &
1#
#460
0#
#465
b1101 "
b1101 &
1#
#470
0#
#475
b1110 "
b1110 &
1#
#480
0#
#485
b1111 "
b1111 &
1#
#490
0#
#495
b0 "
b0 &
1#
#500
0#
#505
b1 "
b1 &
1#
#510
0#
#515
1!
b10 "
b10 &
1#
